{"stage1/test_f1":0.6800136476036338,"stage2/raw_hard_mask_block3":"[0.0, 0.0, 1.0, 0.0, 0.0, 0.0, 0.0, 0.0, 0.0, 1.0, 0.0, 0.0, 0.0, 0.0, 0.0, 0.0, 0.0, 1.0, 0.0, 0.0, 0.0, 1.0, 1.0, 0.0, 0.0, 0.0, 1.0, 1.0, 0.0, 0.0, 1.0, 0.0, 1.0, 1.0, 0.0, 1.0, 0.0, 0.0, 1.0, 0.0, 0.0, 0.0, 0.0, 1.0, 1.0, 1.0, 1.0, 1.0, 1.0, 0.0, 1.0, 1.0, 1.0, 0.0, 1.0, 1.0, 0.0, 0.0, 1.0, 1.0, 0.0, 0.0, 1.0, 0.0, 1.0, 1.0, 0.0, 0.0, 1.0, 0.0, 0.0, 0.0, 0.0, 1.0, 0.0, 1.0, 1.0, 0.0, 0.0, 1.0, 0.0, 0.0, 0.0, 1.0, 1.0, 0.0, 1.0, 0.0, 1.0, 0.0, 0.0, 0.0, 1.0, 0.0, 1.0, 0.0, 0.0, 1.0, 1.0, 1.0, 0.0, 1.0, 1.0, 0.0, 1.0, 0.0, 1.0, 0.0, 0.0, 0.0, 0.0, 0.0, 0.0, 1.0, 1.0, 0.0, 1.0, 0.0, 1.0, 0.0, 0.0, 1.0, 0.0, 1.0, 0.0, 1.0, 0.0, 0.0]","stage2/train_loss":0.8232123994502603,"model_param_count_pruned":13875,"stage2/best_val_loss":1.7536408680217677,"stage2/raw_hard_mask_block4":"[1.0, 0.0, 1.0, 0.0, 1.0, 0.0, 0.0, 1.0, 1.0, 1.0, 1.0, 0.0, 1.0, 1.0, 1.0, 1.0, 1.0, 1.0, 1.0, 1.0, 1.0, 1.0, 1.0, 0.0, 1.0, 0.0, 1.0, 1.0, 1.0, 1.0, 1.0, 0.0, 1.0, 0.0, 1.0, 1.0, 0.0, 0.0, 1.0, 1.0, 0.0, 1.0, 0.0, 0.0, 1.0, 0.0, 1.0, 0.0, 1.0, 1.0, 1.0, 1.0, 0.0, 0.0, 0.0, 1.0, 0.0, 0.0, 1.0, 1.0, 1.0, 0.0, 0.0, 0.0, 1.0, 1.0, 1.0, 0.0, 0.0, 1.0, 0.0, 0.0, 0.0, 1.0, 0.0, 0.0, 0.0, 0.0, 1.0, 1.0, 1.0, 0.0, 0.0, 0.0, 1.0, 0.0, 1.0, 1.0, 1.0, 1.0, 1.0, 1.0, 1.0, 0.0, 0.0, 0.0, 1.0, 0.0, 0.0, 1.0, 1.0, 1.0, 0.0, 0.0, 1.0, 0.0, 1.0, 1.0, 0.0, 1.0, 1.0, 1.0, 1.0, 0.0, 1.0, 1.0, 1.0, 1.0, 0.0, 1.0, 0.0, 1.0, 0.0, 0.0, 1.0, 1.0, 1.0, 0.0]","model_param_count":13875,"val_loss":1.7183176904150532,"stage1_test_loss":0.6567373658043401,"stage2/test_f1":0.6823810356802511,"stage":3,"stage2/test_loss":0.6322282494143197,"stage2/epoch":45,"stage1_test_f1":0.6800136476036338,"stage2/lr_gumbel":0.001,"_timestamp":1.7768897612453582e+09,"model_param_count_dense":36998,"stage2/raw_hard_mask_block2":"[1.0, 0.0, 1.0, 1.0, 1.0, 1.0, 1.0, 0.0, 0.0, 1.0, 0.0, 0.0, 1.0, 1.0, 1.0, 1.0, 0.0, 1.0, 0.0, 1.0, 0.0, 1.0, 0.0, 1.0, 0.0, 0.0, 0.0, 1.0, 1.0, 1.0, 1.0, 1.0, 0.0, 1.0, 1.0, 1.0, 1.0, 0.0, 1.0, 0.0, 0.0, 0.0, 0.0, 1.0, 1.0, 1.0, 1.0, 1.0, 0.0, 1.0, 1.0, 1.0, 1.0, 0.0, 0.0, 1.0, 0.0, 1.0, 1.0, 1.0, 1.0, 0.0, 0.0, 1.0]","stage3_test_f1":0.6875821546273228,"lr_loaded_weights":0.0001,"stage2_test_acc":79.74240082431736,"stage2_test_loss":0.6322282494143197,"stage2/block3_Pruned_%":58.59375,"stage_3_prunedseparableconvcnn/confusion_matrix_table":{"sha256":"9fde704655f29100a42c38cffcb5ee41ecfb3dbcc0703ddb137e62f8ca719fc5","path":"media/table/stage_3_prunedseparableconvcnn/confusion_matrix_table_15_9fde704655f29100a42c.table.json","nrows":64,"_type":"table-file","_latest_artifact_path":"wandb-client-artifact://rb2j5yyr5oftm2ecf2w1bz9wvv4e9akhdgilrlzgh5o3bgjhm88id7dwjwp7rbbq62prwsv6lasled8zfphl19ywty7yd2gyig51xjekgjznuwu6vr3t9edeu8b1shst:latest/stage_3_prunedseparableconvcnn/confusion_matrix_table.table.json","artifact_path":"wandb-client-artifact://30r15p4mxteoeeqkm3ey9x8nzsp11egauomt1iy5pgaekofcile4uc3h4vfqgfkrlt9qm09stzjayiiiehmofovdk85jvi5weujbgr6yi6fwh43j5g4hqs9kdxnk3o25/stage_3_prunedseparableconvcnn/confusion_matrix_table.table.json","ncols":3,"log_mode":"IMMUTABLE","size":2015},"stage2/block2_Pruned_%":37.5,"stage_1_separableconvcnn/confusion_matrix_table":{"sha256":"22c73a0123b0ad491f7a329715df7bd98ee64ccdfae8a04eeedeedfdab902393","_latest_artifact_path":"wandb-client-artifact://1c5fwgo9k97hycscyjl0qgt5z00ymjlqm58942ohhqxdj7ant9mkprcpb0hzqbjwjjessgeaonti360kd4vpup2irledvg1pz0twx8umr93s88m7feot1asig49sxlir:latest/stage_1_separableconvcnn/confusion_matrix_table.table.json","log_mode":"IMMUTABLE","_type":"table-file","path":"media/table/stage_1_separableconvcnn/confusion_matrix_table_1_22c73a0123b0ad491f7a.table.json","nrows":64,"artifact_path":"wandb-client-artifact://wzkxfy14w1lmpdm9xf0fd3bxejlnswbxzlxqp9bniyrdsraw5nte9d13nm8t57gk4y3pire6syabzqcrg47cjoi4x2wysbnqwuy34rmn8ytsozupixyyymi950al27io/stage_1_separableconvcnn/confusion_matrix_table.table.json","size":2014,"ncols":3},"stage2/mask_l1":0.46183300018310547,"stage2/val_loss":1.87517957355076,"stage2/stage_number":2,"Total_Pruned_%":47.18750000000001,"stage2/lr_backbone":0.0001,"final_summary_log_path":"/home/qphan/master-thesis/models/wear_best_model_three_stage_channel_subject10_val_final_summary_val_10.txt","block4_Pruned_%":40.625,"stage3_test_loss":0.6175261172942437,"val_acc":46.07577807848444,"_step":17,"stage1_test_acc":78.78413189077794,"train_loss":0.6425951159019508,"_wandb":{"runtime":243},"stage2/final_mask_keep_ratio_block4":0.59375,"stage1/test_acc":78.78413189077794,"stage2/train_acc":62.19741503869525,"best_val_loss":1.7152699340180229,"stage2/val_acc":42.52368064952638,"block3_Pruned_%":58.59375,"stage3_test_acc":79.14477073673365,"stage2/test_acc":79.74240082431736,"stage2/block4_Pruned_%":40.625,"stage2_test_f1":0.6823810356802511,"stage1/test_loss":0.6567373658043401,"stage2/final_mask_keep_ratio_block3":0.4140625,"stage2/final_mask_keep_ratio_block2":0.625,"stage2/best_epoch":39,"stage2/Total_Pruned_%":47.18750000000001,"block2_Pruned_%":37.5,"model_param_reduction_pct":62.49797286339802,"train_acc":67.67610791124834,"_runtime":243,"stage1/use_pretrain_model":false,"epoch":15,"stage2/purpose":"train channel-pruning model with masking"}