{"stage1_test_loss":0.2309558221050661,"stage2/val_acc":62.10268948655257,"stage_1_separableconvcnn/confusion_matrix_table":{"size":1367,"_latest_artifact_path":"wandb-client-artifact://8ulpyzy338b8we9r7yurxn48eku8mgnhajtyizaqubvcq3v0912zvbxbolvntlyqdrjfal5e4xc570teftfxhym44utsb9sde2cgxlyzvf5sl1r9go3psq1onjdbus06:latest/stage_1_separableconvcnn/confusion_matrix_table.table.json","ncols":3,"path":"media/table/stage_1_separableconvcnn/confusion_matrix_table_1_dcd6f175053c8027eb08.table.json","sha256":"dcd6f175053c8027eb0814c6a2f5d266080369994b8bde5f57a254e8b8525d3d","log_mode":"IMMUTABLE","artifact_path":"wandb-client-artifact://5u10k9i2x1zmpo2zw31ebe34umc74lc2aymnie0nhvzn8q0ez5kgs895nmrgfvrwgwxckzxeynxnezae0i96ah3pm8vetaj8d9pgbsmsjq8xkielxqpo03la87kb890e/stage_1_separableconvcnn/confusion_matrix_table.table.json","_type":"table-file","nrows":36},"stage2/raw_hard_mask_block2":"[1.0, 0.0, 0.0, 0.0, 0.0, 0.0, 1.0, 0.0, 0.0, 0.0, 1.0, 0.0, 0.0, 1.0, 1.0, 0.0, 0.0, 0.0, 0.0, 0.0, 0.0, 1.0, 0.0, 0.0, 1.0, 0.0, 0.0, 1.0, 0.0, 0.0, 0.0, 1.0, 0.0, 1.0, 0.0, 1.0, 0.0, 0.0, 0.0, 0.0, 0.0, 1.0, 0.0, 0.0, 0.0, 0.0, 1.0, 0.0, 1.0, 1.0, 0.0, 0.0, 0.0, 0.0, 1.0, 0.0, 0.0, 1.0, 1.0, 0.0, 0.0, 0.0, 1.0, 0.0]","stage2/purpose":"train channel-pruning model with masking","stage1/use_pretrain_model":false,"model_param_count_dense":36868,"stage1_test_acc":92.02578893790296,"stage2/best_epoch":22,"stage3_test_loss":0.3404407297337526,"stage2/test_acc":62.94536817102138,"_timestamp":1.7758724308167934e+09,"stage":3,"train_acc":86.25954198473282,"block3_Pruned_%":75,"stage2/final_mask_keep_ratio_block2":0.296875,"stage2/train_acc":62.81146478467521,"best_val_loss":0.529004327866333,"final_summary_log_path":"/home/qphan/master-thesis/models/uci_best_model_three_stage_channel_subject25_val_final_summary_val_25.txt","stage2/final_mask_keep_ratio_block3":0.25,"_step":16,"stage2/block3_Pruned_%":75,"model_param_reduction_pct":73.5407399370728,"epoch":25,"stage2/mask_l1":0.44340020418167114,"stage2/raw_hard_mask_block4":"[0.0, 1.0, 1.0, 1.0, 0.0, 0.0, 0.0, 1.0, 1.0, 1.0, 0.0, 1.0, 1.0, 0.0, 1.0, 0.0, 0.0, 0.0, 1.0, 1.0, 0.0, 0.0, 0.0, 0.0, 0.0, 1.0, 1.0, 1.0, 1.0, 1.0, 1.0, 0.0, 0.0, 1.0, 0.0, 0.0, 0.0, 0.0, 0.0, 0.0, 1.0, 0.0, 0.0, 1.0, 0.0, 1.0, 0.0, 0.0, 0.0, 1.0, 1.0, 1.0, 0.0, 0.0, 0.0, 1.0, 1.0, 1.0, 0.0, 1.0, 0.0, 0.0, 1.0, 1.0, 1.0, 0.0, 1.0, 1.0, 0.0, 1.0, 0.0, 0.0, 1.0, 0.0, 1.0, 0.0, 1.0, 1.0, 1.0, 0.0, 1.0, 1.0, 1.0, 1.0, 1.0, 1.0, 0.0, 1.0, 0.0, 0.0, 1.0, 1.0, 1.0, 1.0, 0.0, 1.0, 1.0, 1.0, 1.0, 0.0, 1.0, 1.0, 0.0, 1.0, 1.0, 1.0, 1.0, 1.0, 1.0, 1.0, 1.0, 1.0, 0.0, 0.0, 1.0, 1.0, 1.0, 0.0, 1.0, 1.0, 1.0, 1.0, 0.0, 0.0, 1.0, 1.0, 1.0, 1.0]","train_loss":0.2943065040619422,"stage2/val_loss":0.5926831156939888,"model_param_count":9755,"block2_Pruned_%":70.3125,"Total_Pruned_%":60.3125,"stage2/test_loss":0.7050230206841427,"stage2/lr_backbone":0.0001,"_wandb":{"runtime":29},"stage2/block4_Pruned_%":40.625,"stage3_test_acc":88.42891075670173,"stage1_test_f1":0.9219480846720957,"stage1/test_acc":92.02578893790296,"lr_loaded_weights":0.0001,"model_param_count_pruned":9755,"stage1/test_f1":0.9219480846720957,"stage2_test_f1":0.573273493087391,"stage2/raw_hard_mask_block3":"[0.0, 0.0, 0.0, 0.0, 0.0, 1.0, 0.0, 1.0, 1.0, 0.0, 0.0, 0.0, 1.0, 0.0, 0.0, 0.0, 0.0, 1.0, 0.0, 1.0, 0.0, 1.0, 0.0, 0.0, 0.0, 0.0, 0.0, 1.0, 0.0, 0.0, 0.0, 0.0, 0.0, 1.0, 0.0, 0.0, 0.0, 0.0, 1.0, 0.0, 0.0, 0.0, 1.0, 0.0, 1.0, 1.0, 0.0, 0.0, 0.0, 1.0, 0.0, 0.0, 0.0, 0.0, 0.0, 0.0, 1.0, 0.0, 0.0, 1.0, 0.0, 0.0, 1.0, 0.0, 1.0, 0.0, 0.0, 0.0, 0.0, 1.0, 0.0, 0.0, 0.0, 1.0, 0.0, 0.0, 0.0, 1.0, 1.0, 0.0, 0.0, 1.0, 0.0, 0.0, 0.0, 0.0, 0.0, 0.0, 0.0, 0.0, 1.0, 0.0, 0.0, 0.0, 0.0, 0.0, 1.0, 1.0, 0.0, 0.0, 0.0, 1.0, 0.0, 1.0, 0.0, 0.0, 0.0, 0.0, 1.0, 1.0, 0.0, 0.0, 0.0, 1.0, 0.0, 0.0, 0.0, 0.0, 0.0, 0.0, 0.0, 0.0, 0.0, 0.0, 1.0, 0.0, 0.0, 0.0]","stage2/best_val_loss":0.5677265003346326,"stage2/test_f1":0.573273493087391,"stage2/train_loss":0.8778814981362498,"stage2/lr_gumbel":0.001,"val_acc":81.41809290953545,"stage3_test_f1":0.8867980424437203,"block4_Pruned_%":40.625,"val_loss":0.5644282721515863,"stage2/block2_Pruned_%":70.3125,"stage2/epoch":30,"stage2_test_loss":0.7050230206841427,"stage_3_prunedseparableconvcnn/confusion_matrix_table":{"log_mode":"IMMUTABLE","ncols":3,"path":"media/table/stage_3_prunedseparableconvcnn/confusion_matrix_table_14_1f6f68b6228d66e8bc88.table.json","size":1368,"nrows":36,"_latest_artifact_path":"wandb-client-artifact://h8dunwlapakr2nuzpv5bqhad94e0u3rlz0ca480eheo7ma0rib6sut450xuqqdr921u045ghcc7kb8k71ev3kr6cui2sln4uhbbm1z0d1ioc6kgm3cyfhlqqk9wh4dms:latest/stage_3_prunedseparableconvcnn/confusion_matrix_table.table.json","sha256":"1f6f68b6228d66e8bc88610415c2755f7f20bf5b29efdc886c74dd22a3adb5b1","artifact_path":"wandb-client-artifact://zjy2k2m0yh26vquuc9kvc7kx74wtukt42vi3qdszrj93dc53gl307uirhb9ib1i8t153eqbywlkbcozd7xyzx0qkr0wpcwbz9fi9r696dhfcag9tu8v7vaqli7uzm1un/stage_3_prunedseparableconvcnn/confusion_matrix_table.table.json","_type":"table-file"},"stage2/Total_Pruned_%":60.3125,"stage2_test_acc":62.94536817102138,"stage2/stage_number":2,"stage1/test_loss":0.2309558221050661,"_runtime":29,"stage2/final_mask_keep_ratio_block4":0.59375}