{"stage2/best_val_loss":0.7865619681486117,"stage2/block4_Pruned_%":27.34375,"model_param_count":15178,"stage2/lr_gumbel":0.001,"_wandb":{"runtime":349},"block2_Pruned_%":50,"block3_Pruned_%":58.59375,"block4_Pruned_%":27.34375,"lr_loaded_weights":0.0001,"stage2_test_loss":0.638603678515727,"stage2/raw_hard_mask_block3":"[1.0, 1.0, 0.0, 1.0, 0.0, 1.0, 1.0, 0.0, 0.0, 0.0, 0.0, 1.0, 0.0, 1.0, 1.0, 1.0, 0.0, 0.0, 1.0, 0.0, 0.0, 0.0, 1.0, 1.0, 0.0, 1.0, 1.0, 0.0, 1.0, 0.0, 0.0, 0.0, 0.0, 1.0, 0.0, 0.0, 0.0, 1.0, 0.0, 0.0, 1.0, 1.0, 0.0, 0.0, 1.0, 0.0, 1.0, 0.0, 0.0, 0.0, 0.0, 1.0, 0.0, 1.0, 0.0, 0.0, 1.0, 0.0, 1.0, 0.0, 0.0, 0.0, 1.0, 1.0, 1.0, 1.0, 0.0, 0.0, 1.0, 0.0, 0.0, 1.0, 0.0, 0.0, 0.0, 0.0, 1.0, 1.0, 0.0, 1.0, 0.0, 0.0, 1.0, 1.0, 0.0, 0.0, 0.0, 0.0, 1.0, 1.0, 1.0, 1.0, 0.0, 1.0, 0.0, 0.0, 1.0, 0.0, 1.0, 0.0, 0.0, 0.0, 1.0, 0.0, 0.0, 1.0, 1.0, 0.0, 0.0, 0.0, 1.0, 1.0, 1.0, 0.0, 0.0, 1.0, 0.0, 0.0, 0.0, 1.0, 0.0, 0.0, 0.0, 0.0, 0.0, 1.0, 0.0, 1.0]","stage3_test_acc":79.03142709943329,"_timestamp":1.7763820902990577e+09,"stage_1_separableconvcnn/confusion_matrix_table":{"_latest_artifact_path":"wandb-client-artifact://83wck1ewdhz8xsktvfezvlrk3zgvt2s2uw5vdhqrw3g5yb1rtd0901tucrtz2qcyh4b556oqeinzu01ep3om09lugiy1vr3ojvxmlli6o6bqntng3kq1s6uzd2cjldtt:latest/stage_1_separableconvcnn/confusion_matrix_table.table.json","log_mode":"IMMUTABLE","artifact_path":"wandb-client-artifact://zcglctemx6d7u9dsn7nz05rtqfu4nl1b0qplhdau43vmd4e75ap6srcq6s6cwhrr36s1n45s3jikp7w1xgrj7z19j1b46rgl3h1lhqoaxwpqwpodm984rqny3p2gchif/stage_1_separableconvcnn/confusion_matrix_table.table.json","_type":"table-file","nrows":64,"ncols":3,"size":2015,"sha256":"2a6858e2e20d070a469ce3e009e9e7c4c07c20ff1c4dc5f7932d10bd4b5c53d8","path":"media/table/stage_1_separableconvcnn/confusion_matrix_table_1_2a6858e2e20d070a469c.table.json"},"train_acc":70.41625174268074,"stage1_test_acc":80.30911901081916,"stage2/mask_l1":0.49278363585472107,"stage2_test_f1":0.677677646704911,"stage2/stage_number":2,"stage1/test_loss":0.6201939224674798,"stage2/val_loss":0.7917436183355897,"stage1_test_loss":0.6201939224674798,"stage2/final_mask_keep_ratio_block4":0.7265625,"stage1_test_f1":0.6875232264811629,"stage3_test_loss":0.5974939217738181,"train_loss":0.5904291231136971,"stage2/epoch":60,"stage1/test_f1":0.6875232264811629,"stage2/purpose":"train channel-pruning model with masking","stage2/raw_hard_mask_block2":"[0.0, 0.0, 1.0, 0.0, 0.0, 0.0, 0.0, 1.0, 0.0, 1.0, 1.0, 1.0, 0.0, 0.0, 0.0, 1.0, 1.0, 0.0, 1.0, 1.0, 0.0, 0.0, 0.0, 1.0, 1.0, 0.0, 1.0, 1.0, 0.0, 1.0, 1.0, 0.0, 0.0, 1.0, 1.0, 1.0, 1.0, 0.0, 1.0, 0.0, 1.0, 0.0, 0.0, 0.0, 0.0, 1.0, 1.0, 1.0, 1.0, 0.0, 0.0, 0.0, 1.0, 1.0, 1.0, 1.0, 1.0, 1.0, 0.0, 1.0, 0.0, 0.0, 0.0, 0.0]","stage2/val_acc":59.74304068522484,"val_acc":62.802080146833895,"Total_Pruned_%":44.375,"model_param_count_pruned":15178,"final_summary_log_path":"/home/qphan/master-thesis/models/wear_best_model_three_stage_channel_subject12_val_final_summary_val_12.txt","stage2/test_loss":0.638603678515727,"stage3_test_f1":0.6893534515542534,"stage2/best_epoch":50,"stage1/test_acc":80.30911901081916,"val_loss":0.7636756541605716,"model_param_reduction_pct":58.97616087356074,"stage2/lr_backbone":0.0001,"model_param_count_dense":36998,"stage2/test_acc":78.46470891293148,"stage2_test_acc":78.46470891293148,"stage1/use_pretrain_model":false,"best_val_loss":0.7428503385301977,"stage2/block3_Pruned_%":58.59375,"stage2/test_f1":0.677677646704911,"stage2/raw_hard_mask_block4":"[1.0, 1.0, 1.0, 1.0, 1.0, 0.0, 1.0, 1.0, 0.0, 1.0, 1.0, 0.0, 1.0, 1.0, 1.0, 1.0, 0.0, 1.0, 1.0, 1.0, 1.0, 1.0, 1.0, 0.0, 0.0, 0.0, 1.0, 1.0, 0.0, 0.0, 0.0, 1.0, 1.0, 0.0, 1.0, 1.0, 0.0, 1.0, 1.0, 1.0, 1.0, 1.0, 0.0, 1.0, 1.0, 0.0, 1.0, 1.0, 1.0, 1.0, 1.0, 1.0, 1.0, 1.0, 0.0, 0.0, 1.0, 1.0, 1.0, 0.0, 1.0, 1.0, 0.0, 1.0, 1.0, 1.0, 0.0, 1.0, 0.0, 1.0, 0.0, 1.0, 1.0, 1.0, 1.0, 1.0, 0.0, 1.0, 0.0, 1.0, 1.0, 1.0, 1.0, 1.0, 1.0, 1.0, 1.0, 1.0, 1.0, 1.0, 1.0, 1.0, 0.0, 0.0, 0.0, 0.0, 0.0, 1.0, 1.0, 1.0, 1.0, 1.0, 1.0, 1.0, 1.0, 0.0, 1.0, 1.0, 1.0, 1.0, 1.0, 1.0, 0.0, 0.0, 1.0, 1.0, 0.0, 1.0, 0.0, 0.0, 1.0, 1.0, 1.0, 1.0, 1.0, 1.0, 1.0, 0.0]","stage_3_prunedseparableconvcnn/confusion_matrix_table":{"nrows":64,"artifact_path":"wandb-client-artifact://sl0eosn8qeedf5nxsphshztflrqvkrir6uxqcso01ycmw9epnj812bqeqyopfnb3nosgja654iux9dx3hf7ukbtozv70i16okon0torz8c6iq8za6r24bylt4a5grmkl/stage_3_prunedseparableconvcnn/confusion_matrix_table.table.json","_type":"table-file","size":2011,"sha256":"8a9bca2cf8dbb73c72ac65dc228e084cbe2f880755b942415cac626771cffcdf","_latest_artifact_path":"wandb-client-artifact://3urhbwl88nzqj1h75jx5px2170a9gu0fa3hwexlt53qdbzwb2ltvnb9l3dq57479e6uco3d0uv608mord6rjno535xclfz5y07v0ssr7e8oooc4hhpf3oz6qqoqey5ju:latest/stage_3_prunedseparableconvcnn/confusion_matrix_table.table.json","path":"media/table/stage_3_prunedseparableconvcnn/confusion_matrix_table_24_8a9bca2cf8dbb73c72ac.table.json","ncols":3,"log_mode":"IMMUTABLE"},"stage2/train_acc":64.53296156144194,"epoch":45,"stage2/final_mask_keep_ratio_block2":0.5,"stage2/train_loss":0.8102865071819969,"_step":26,"stage2/block2_Pruned_%":50,"stage2/final_mask_keep_ratio_block3":0.4140625,"stage":3,"_runtime":349,"stage2/Total_Pruned_%":44.375}