{"stage2/final_mask_keep_ratio_block3":0.515625,"train_acc":89.73042362002568,"stage5_test_acc":90.32914828639294,"_wandb":{"runtime":61},"mask_l1":0.3359375,"stage_3_separableconvcnn/confusion_matrix_table":{"log_mode":"IMMUTABLE","size":1365,"ncols":3,"artifact_path":"wandb-client-artifact://2cxkz442s6d03sqnxj4fetb3h7f6rnsmdtw9sot9fxdyl3g5x09lq51895k4tc6h1uefv1xwfekerzsc6eh1rkedad33cumga586g0n5t7yk7w8z03t2mzkp6c0qndu7/stage_3_separableconvcnn/confusion_matrix_table.table.json","sha256":"0d626a69498db7915387be765116a9eda7cecc31c7b2bc1eb5b62cd6760f7d09","path":"media/table/stage_3_separableconvcnn/confusion_matrix_table_12_0d626a69498db7915387.table.json","nrows":36,"_type":"table-file","_latest_artifact_path":"wandb-client-artifact://h24jlmh40fo5km5ysd0drhcqnoi2mx1t2u8atcm4abcx1h973bgbyv6se0nhcq18kgzembt9idutcabkmwj46wh3678w3ugxfk37xqjn1xwf6wrtk5ri2n22p5jhwk48:latest/stage_3_separableconvcnn/confusion_matrix_table.table.json"},"stage2/test_f1":0.8972987686877901,"stage_5_prunedseparableconvcnn/confusion_matrix_table":{"nrows":36,"path":"media/table/stage_5_prunedseparableconvcnn/confusion_matrix_table_29_dbffe84bca812a9147a1.table.json","log_mode":"IMMUTABLE","artifact_path":"wandb-client-artifact://8pru1rnv8i2bqxp74wn6yzfmp0s1i9m3xcs3qunt0cvvmm2oq8apov5is2klqpu7urj8iitbf56xn64qa5vnzgmsm2kgyh0l5y9a6y71isy8lcevwxxb9nczvd6ntyxy/stage_5_prunedseparableconvcnn/confusion_matrix_table.table.json","sha256":"dbffe84bca812a9147a1bd62b69dd0ef061f34453075f1d47a6c1b87861af3c3","size":1367,"ncols":3,"_type":"table-file","_latest_artifact_path":"wandb-client-artifact://68sny20j6cao704los98rf4amal3od4krve55l9wasxpqcx4ofln8irm8clgq4hl4zwhe0gfflwoe2dku3h7n4a3fpo9hu1jfwa7ca2osuemg88lnejoi9clj166cn16:latest/stage_5_prunedseparableconvcnn/confusion_matrix_table.table.json"},"final_channel_mask_block3":[1,1,1,1,1,1,0,0,1,1,1,1,1,1,0,0,0,0,1,1,0,0,1,0,1,1,0,1,1,0,1,0,1,1,0,0,1,1,0,1,0,1,0,1,0,0,1,0,0,0,1,0,1,1,1,0,0,1,1,1,0,0,0,0,0,1,0,1,0,0,1,0,1,0,0,1,0,1,0,1,1,1,1,0,1,0,0,0,1,1,0,0,0,0,0,0,0,1,1,0,0,1,1,0,0,0,1,1,1,1,0,0,1,0,1,1,1,1,0,1,0,0,1,1,0,1,1,0],"stage5_test_loss":0.2821908436880054,"model_param_count_dense":36868,"stage1/test_loss":0.22617445322285173,"lr_loaded_weights":0.0001,"stage1_test_acc":91.07567017305735,"stage2/best_val_loss":0.4730025091129314,"stage2/mask_l1":0.5468688011169434,"hard_bin_mask":[1,1,1,1,1,1,1,1,1,1,0,1,1,1,1,1,1,1,1,1,1,1,1,1,1,1,1,0,0,1,1,1,1,1,1,1,1,1,1,1,0,0,0,1,0,1,1,1,0,0,0,0,1,0,0,0,0,0,0,0,0,1,0,1,0,0,0,1,0,0,0,0,0,0,0,0,0,0,0,0,0,0,0,0,0,0,0,0,0,0,0,0,0,0,0,0,0,0,0,0,0,0,0,0,0,0,0,0,0,0,0,0,0,0,0,0,0,0,0,0,0,0,0,0,0,0,0,0],"final_channel_mask_block4":[1,1,0,1,1,1,0,1,0,1,1,0,1,1,0,1,1,1,0,1,1,1,1,0,1,0,1,1,1,0,1,0,0,0,1,1,1,1,0,0,1,0,0,0,0,0,0,1,1,0,0,1,1,1,1,1,1,0,1,1,0,1,1,1,0,1,1,0,1,0,1,1,0,1,0,0,0,1,1,1,1,0,1,1,1,1,1,1,1,0,1,0,0,1,1,0,1,1,0,0,1,1,0,1,1,1,1,0,0,1,1,1,0,1,1,1,1,0,1,1,0,1,1,0,0,0,0,0],"stage2/best_epoch":57,"stage2/lr_backbone":0.0001,"stage2/train_loss":0.479907255308925,"stage2/raw_hard_mask_block3":"[1.0, 1.0, 1.0, 1.0, 1.0, 1.0, 0.0, 0.0, 1.0, 1.0, 1.0, 1.0, 1.0, 1.0, 0.0, 0.0, 0.0, 0.0, 1.0, 1.0, 0.0, 0.0, 1.0, 0.0, 1.0, 1.0, 0.0, 1.0, 1.0, 0.0, 1.0, 0.0, 1.0, 1.0, 0.0, 0.0, 1.0, 1.0, 0.0, 1.0, 0.0, 1.0, 0.0, 1.0, 0.0, 0.0, 1.0, 0.0, 0.0, 0.0, 1.0, 0.0, 1.0, 1.0, 1.0, 0.0, 0.0, 1.0, 1.0, 1.0, 0.0, 0.0, 0.0, 0.0, 0.0, 1.0, 0.0, 1.0, 0.0, 0.0, 1.0, 0.0, 1.0, 0.0, 0.0, 1.0, 0.0, 1.0, 0.0, 1.0, 1.0, 1.0, 1.0, 0.0, 1.0, 0.0, 0.0, 0.0, 1.0, 1.0, 0.0, 0.0, 0.0, 0.0, 0.0, 0.0, 0.0, 1.0, 1.0, 0.0, 0.0, 1.0, 1.0, 0.0, 0.0, 0.0, 1.0, 1.0, 1.0, 1.0, 0.0, 0.0, 1.0, 0.0, 1.0, 1.0, 1.0, 1.0, 0.0, 1.0, 0.0, 0.0, 1.0, 1.0, 0.0, 1.0, 1.0, 0.0]","stage2/final_mask_keep_ratio_block4":0.6171875,"stage2/epoch":60,"_runtime":61,"stage2/Total_Pruned_%":40.93750000000001,"lr":0.001,"lr_backbone":0.0001,"stage2/block2_Pruned_%":31.25,"stage1_test_loss":0.22617445322285173,"_timestamp":1.776708006971643e+09,"stage2/block4_Pruned_%":38.28125,"stage2/test_loss":0.3111239322683676,"best_val_loss":0.403093409678104,"val_acc":85.92375366568915,"stage1/test_acc":91.07567017305735,"stage5_test_f1":0.9058765598294248,"stage2/test_acc":89.61655921275874,"model_param_reduction_pct":56.2601714223717,"stage2/val_loss":0.5012835215263702,"stage1/use_pretrain_model":false,"_step":30,"epoch":15,"stage1_test_f1":0.9123850769801085,"stage2/final_mask_keep_ratio_block2":0.6875,"stage2/train_acc":83.02667237198688,"train_loss":0.24079239610096406,"stage2/block3_Pruned_%":48.4375,"stage1/test_f1":0.9123850769801085,"stage2/purpose":"train channel-pruning model with masking","final_channel_mask_block2":[1,1,1,1,0,1,1,1,0,1,0,1,0,0,1,1,1,0,1,1,1,1,1,0,0,0,0,1,1,1,0,0,0,1,1,1,1,1,0,1,0,0,0,1,1,0,0,1,1,1,1,1,0,1,1,1,1,1,1,1,1,1,1,1],"val_loss":0.40756234220745274,"stage2/stage_number":2,"stage2/raw_hard_mask_block2":"[1.0, 1.0, 1.0, 1.0, 0.0, 1.0, 1.0, 1.0, 0.0, 1.0, 0.0, 1.0, 0.0, 0.0, 1.0, 1.0, 1.0, 0.0, 1.0, 1.0, 1.0, 1.0, 1.0, 0.0, 0.0, 0.0, 0.0, 1.0, 1.0, 1.0, 0.0, 0.0, 0.0, 1.0, 1.0, 1.0, 1.0, 1.0, 0.0, 1.0, 0.0, 0.0, 0.0, 1.0, 1.0, 0.0, 0.0, 1.0, 1.0, 1.0, 1.0, 1.0, 0.0, 1.0, 1.0, 1.0, 1.0, 1.0, 1.0, 1.0, 1.0, 1.0, 1.0, 1.0]","stage_1_separableconvcnn/confusion_matrix_table":{"size":1366,"log_mode":"IMMUTABLE","sha256":"ee0fa33fc929b82f93f642ef91fbb8aa9f03d6057574e4a8afa65bbfb16ea3b6","path":"media/table/stage_1_separableconvcnn/confusion_matrix_table_1_ee0fa33fc929b82f93f6.table.json","nrows":36,"artifact_path":"wandb-client-artifact://9q73c4oopzt13b41fiah14kpz41zjzle0w6avmgq2h4jsv318kcgmg40pk0ktogjl0ror7skq07d7mkp7uvw6p2r5px0wonwg7n00ehlat1gixtpmbb63jqa1da3m9gh/stage_1_separableconvcnn/confusion_matrix_table.table.json","_latest_artifact_path":"wandb-client-artifact://emimruzw415tzkofjj291kz1va8dew3tkwkoloeqxcbez7cyks52xqate8vnxpxo7xl6jp824kgqanortwokskyfq8ud5n7sbqkvji4vca5xifoe6mteomiohrth94s7:latest/stage_1_separableconvcnn/confusion_matrix_table.table.json","ncols":3,"_type":"table-file"},"lr_gumbel_bin":0.001,"stage2/val_acc":80.64516129032258,"stage2/lr_gumbel":0.001,"stage2/raw_hard_mask_block4":"[1.0, 1.0, 0.0, 1.0, 1.0, 1.0, 0.0, 1.0, 0.0, 1.0, 1.0, 0.0, 1.0, 1.0, 0.0, 1.0, 1.0, 1.0, 0.0, 1.0, 1.0, 1.0, 1.0, 0.0, 1.0, 0.0, 1.0, 1.0, 1.0, 0.0, 1.0, 0.0, 0.0, 0.0, 1.0, 1.0, 1.0, 1.0, 0.0, 0.0, 1.0, 0.0, 0.0, 0.0, 0.0, 0.0, 0.0, 1.0, 1.0, 0.0, 0.0, 1.0, 1.0, 1.0, 1.0, 1.0, 1.0, 0.0, 1.0, 1.0, 0.0, 1.0, 1.0, 1.0, 0.0, 1.0, 1.0, 0.0, 1.0, 0.0, 1.0, 1.0, 0.0, 1.0, 0.0, 0.0, 0.0, 1.0, 1.0, 1.0, 1.0, 0.0, 1.0, 1.0, 1.0, 1.0, 1.0, 1.0, 1.0, 0.0, 1.0, 0.0, 0.0, 1.0, 1.0, 0.0, 1.0, 1.0, 0.0, 0.0, 1.0, 1.0, 0.0, 1.0, 1.0, 1.0, 1.0, 0.0, 0.0, 1.0, 1.0, 1.0, 0.0, 1.0, 1.0, 1.0, 1.0, 0.0, 1.0, 1.0, 0.0, 1.0, 1.0, 0.0, 0.0, 0.0, 0.0, 0.0]","stage":5,"model_param_count_pruned":16126}