{"block4_Pruned_%":82.8125,"stage1/test_loss":0.5326458260416984,"stage2/raw_hard_mask_block4":"[0.0, 0.0, 0.0, 1.0, 0.0, 0.0, 0.0, 0.0, 0.0, 0.0, 1.0, 0.0, 0.0, 0.0, 0.0, 1.0, 1.0, 0.0, 0.0, 0.0, 0.0, 0.0, 1.0, 0.0, 0.0, 1.0, 0.0, 0.0, 0.0, 0.0, 0.0, 0.0, 0.0, 0.0, 0.0, 0.0, 0.0, 0.0, 0.0, 0.0, 0.0, 0.0, 0.0, 1.0, 1.0, 0.0, 0.0, 0.0, 1.0, 0.0, 0.0, 0.0, 0.0, 0.0, 0.0, 0.0, 0.0, 0.0, 0.0, 1.0, 0.0, 0.0, 0.0, 0.0, 0.0, 0.0, 0.0, 0.0, 0.0, 0.0, 0.0, 0.0, 0.0, 0.0, 1.0, 0.0, 0.0, 0.0, 0.0, 1.0, 1.0, 0.0, 1.0, 0.0, 0.0, 0.0, 1.0, 0.0, 1.0, 0.0, 0.0, 0.0, 0.0, 0.0, 0.0, 0.0, 0.0, 0.0, 0.0, 0.0, 0.0, 1.0, 0.0, 0.0, 0.0, 0.0, 0.0, 0.0, 0.0, 0.0, 0.0, 1.0, 0.0, 0.0, 1.0, 0.0, 0.0, 0.0, 0.0, 0.0, 1.0, 1.0, 0.0, 0.0, 0.0, 0.0, 1.0, 0.0]","_runtime":228,"stage2/val_loss":1.3503150646063349,"stage2/val_acc":28.27338129496403,"_timestamp":1.7763697995094008e+09,"stage2/train_acc":38.0660731306658,"stage2/Total_Pruned_%":91.5625,"model_param_count_dense":36998,"stage2/test_acc":64.35857805255023,"stage3_test_loss":1.3581214526582783,"stage2/block2_Pruned_%":98.4375,"stage2/lr_backbone":0.0001,"val_acc":16.954436450839328,"epoch":30,"train_loss":1.524155095997776,"stage2/lr_gumbel":0.001,"stage2/block4_Pruned_%":82.8125,"stage2/mask_l1":0.09297006577253342,"stage2/block3_Pruned_%":96.875,"stage2/train_loss":1.5135178330601762,"best_val_loss":1.5403778100757004,"stage3_test_acc":46.419371458011334,"stage1/test_f1":0.7193666760635133,"model_param_count":2567,"stage2_test_loss":1.0776695578937245,"model_param_reduction_pct":93.0617871236283,"train_acc":28.76351173213815,"stage":3,"stage2/best_val_loss":1.2760663023383783,"stage2/final_mask_keep_ratio_block2":0.015625,"stage2/best_epoch":25,"stage1/test_acc":81.42194744976815,"stage1_test_acc":81.42194744976815,"stage2/stage_number":2,"stage2/raw_hard_mask_block2":"[0.0, 0.0, 0.0, 0.0, 0.0, 0.0, 0.0, 0.0, 0.0, 0.0, 0.0, 0.0, 0.0, 0.0, 0.0, 0.0, 0.0, 0.0, 0.0, 0.0, 0.0, 0.0, 0.0, 0.0, 0.0, 0.0, 1.0, 0.0, 0.0, 0.0, 0.0, 0.0, 0.0, 0.0, 0.0, 0.0, 0.0, 0.0, 0.0, 0.0, 0.0, 0.0, 0.0, 0.0, 0.0, 0.0, 0.0, 0.0, 0.0, 0.0, 0.0, 0.0, 0.0, 0.0, 0.0, 0.0, 0.0, 0.0, 0.0, 0.0, 0.0, 0.0, 0.0, 0.0]","stage1_test_f1":0.7193666760635133,"stage3_test_f1":0.33632735270497827,"block2_Pruned_%":98.4375,"lr_loaded_weights":0.0001,"stage2_test_f1":0.4886123721065966,"stage1/use_pretrain_model":false,"stage2/final_mask_keep_ratio_block3":0.03125,"final_summary_log_path":"/home/qphan/master-thesis/models/wear_best_model_three_stage_channel_subject3_val_final_summary_val_3.txt","stage_1_separableconvcnn/confusion_matrix_table":{"size":2010,"path":"media/table/stage_1_separableconvcnn/confusion_matrix_table_1_186b5618f1f3a59746e8.table.json","_latest_artifact_path":"wandb-client-artifact://bxh3jy4qfuql810u1c3kw4t8gakxweddu5nocs8bxoit3pkqmzio513tw9pnob7hcjq4pqj7kx86k4u764s8hyrleng6ag2rdwgc3gil2zipv9scrhyetgikk00rj50c:latest/stage_1_separableconvcnn/confusion_matrix_table.table.json","_type":"table-file","sha256":"186b5618f1f3a59746e88343f87c53d3e8d7b252cbefb4c5abf36cdb298c892f","nrows":64,"log_mode":"IMMUTABLE","artifact_path":"wandb-client-artifact://hai3zr2x8jssrvuid399bc38shue5n1y2xwrx042shte0o54885fjtuyyu69pl28vo0pel2cxmq0gjnvaxt1nvvfxl656eb96gf8n8wx2dgw7288mlapd73pjpfcwjp6/stage_1_separableconvcnn/confusion_matrix_table.table.json","ncols":3},"stage2/final_mask_keep_ratio_block4":0.171875,"block3_Pruned_%":96.875,"stage2/raw_hard_mask_block3":"[0.0, 0.0, 0.0, 0.0, 0.0, 0.0, 0.0, 0.0, 0.0, 0.0, 0.0, 0.0, 0.0, 0.0, 1.0, 0.0, 0.0, 0.0, 0.0, 0.0, 0.0, 0.0, 0.0, 0.0, 0.0, 0.0, 0.0, 1.0, 0.0, 0.0, 0.0, 0.0, 0.0, 0.0, 0.0, 0.0, 0.0, 0.0, 0.0, 0.0, 0.0, 0.0, 0.0, 0.0, 0.0, 0.0, 0.0, 0.0, 0.0, 0.0, 0.0, 0.0, 0.0, 0.0, 0.0, 0.0, 0.0, 0.0, 0.0, 0.0, 0.0, 0.0, 0.0, 0.0, 0.0, 0.0, 0.0, 0.0, 0.0, 0.0, 0.0, 0.0, 0.0, 0.0, 0.0, 0.0, 0.0, 0.0, 0.0, 0.0, 0.0, 0.0, 0.0, 0.0, 0.0, 0.0, 0.0, 0.0, 0.0, 0.0, 0.0, 0.0, 0.0, 0.0, 1.0, 0.0, 0.0, 0.0, 0.0, 0.0, 0.0, 0.0, 0.0, 0.0, 0.0, 0.0, 0.0, 0.0, 0.0, 0.0, 0.0, 0.0, 0.0, 0.0, 0.0, 0.0, 0.0, 0.0, 1.0, 0.0, 0.0, 0.0, 0.0, 0.0, 0.0, 0.0, 0.0, 0.0]","_step":18,"_wandb":{"runtime":228},"stage2/epoch":35,"stage_3_prunedseparableconvcnn/confusion_matrix_table":{"_latest_artifact_path":"wandb-client-artifact://czghcvwtp0ra2ibucvw99k3gu6sytqui0e0jk76qptswamhg7hp2zewjrzne6ingzreu5cd6zneztqozlca4a4j13o5uxel7o7ukoemadutzke2uhketgys0a01mo7lb:latest/stage_3_prunedseparableconvcnn/confusion_matrix_table.table.json","_type":"table-file","size":2023,"ncols":3,"log_mode":"IMMUTABLE","nrows":64,"path":"media/table/stage_3_prunedseparableconvcnn/confusion_matrix_table_16_1d62d2ed9c50d94e2613.table.json","sha256":"1d62d2ed9c50d94e26132f3054e74ad3acc639da84117bfcfd2418ed712abf33","artifact_path":"wandb-client-artifact://p56fw7xozjl5melwxc813e9066pxcj6locbbnmekp0wtp9hzh7c47zh4e436c4c3q1hudbn0kdoy17xktxlcor302ozgkgv205x9r75jp7ns8ywrz4ycsa9iyyzyfzxl/stage_3_prunedseparableconvcnn/confusion_matrix_table.table.json"},"val_loss":1.9754088138790726,"model_param_count_pruned":2567,"stage2/test_loss":1.0776695578937245,"stage2/test_f1":0.4886123721065966,"stage2_test_acc":64.35857805255023,"stage2/purpose":"train channel-pruning model with masking","Total_Pruned_%":91.5625,"stage1_test_loss":0.5326458260416984}