{"stage_1_separableconvcnn/confusion_matrix_table":{"artifact_path":"wandb-client-artifact://pnhwbdc0xuy3g2uqp47ud52878uqcyg2z9ix0scfcwh558yogivndast6idm3xwd6irgi914v2hkfzn1ndewbttgdb2wyx7bhc7762ee9h7d0vezetisvbee4tuk5flq/stage_1_separableconvcnn/confusion_matrix_table.table.json","nrows":36,"_type":"table-file","path":"media/table/stage_1_separableconvcnn/confusion_matrix_table_1_e8bddad924e757dde1b8.table.json","log_mode":"IMMUTABLE","ncols":3,"sha256":"e8bddad924e757dde1b81f31e031831638259fb4974eb769d521003a409a9b0d","size":1361,"_latest_artifact_path":"wandb-client-artifact://5sxkaivyjgbdwkrqlupjyxpc3q06agnb5m0u7q7mzx7a652xnc3sycxrttmhnap8d0also48ldxcv1ptjw5dgqpc0z4ptpb2ndl6vlwczybx26ho3se6khcls26a7or9:latest/stage_1_separableconvcnn/confusion_matrix_table.table.json"},"lr_loaded_weights":0.0001,"stage2/block2_Pruned_%":73.4375,"model_param_reduction_pct":87.48779429315395,"best_val_loss":0.28646330152863686,"stage2/val_loss":2.577173081470294,"stage1_test_acc":93.95995928062436,"block3_Pruned_%":79.6875,"model_param_count":4613,"stage2/block3_Pruned_%":79.6875,"stage2/final_mask_keep_ratio_block4":0.21875,"stage2/raw_hard_mask_block4":"[0.0, 1.0, 1.0, 0.0, 1.0, 0.0, 0.0, 0.0, 0.0, 0.0, 0.0, 0.0, 0.0, 0.0, 0.0, 0.0, 0.0, 1.0, 0.0, 0.0, 0.0, 0.0, 0.0, 0.0, 1.0, 0.0, 0.0, 0.0, 0.0, 0.0, 1.0, 0.0, 0.0, 0.0, 0.0, 0.0, 0.0, 0.0, 0.0, 0.0, 1.0, 1.0, 0.0, 0.0, 0.0, 1.0, 1.0, 0.0, 0.0, 0.0, 0.0, 0.0, 0.0, 0.0, 1.0, 0.0, 0.0, 1.0, 1.0, 0.0, 0.0, 0.0, 0.0, 0.0, 0.0, 1.0, 1.0, 0.0, 0.0, 0.0, 0.0, 0.0, 0.0, 1.0, 0.0, 0.0, 0.0, 0.0, 0.0, 0.0, 0.0, 0.0, 0.0, 0.0, 1.0, 0.0, 0.0, 0.0, 1.0, 0.0, 0.0, 0.0, 0.0, 0.0, 0.0, 0.0, 0.0, 0.0, 0.0, 0.0, 0.0, 1.0, 0.0, 0.0, 1.0, 0.0, 0.0, 1.0, 1.0, 0.0, 0.0, 1.0, 1.0, 0.0, 0.0, 0.0, 1.0, 1.0, 0.0, 0.0, 1.0, 0.0, 0.0, 1.0, 0.0, 0.0, 0.0, 0.0]","stage2/best_val_loss":1.585636472352268,"_timestamp":1.776801933910021e+09,"model_param_count_pruned":4613,"stage1/test_acc":93.95995928062436,"Total_Pruned_%":77.8125,"block2_Pruned_%":73.4375,"stage2/test_f1":0.3013786284501836,"stage2/lr_gumbel":0.001,"stage3_test_f1":0.9069759682708952,"stage1_test_f1":0.9402865062837908,"model_param_count_dense":36868,"stage":3,"stage2/stage_number":2,"stage2/test_acc":46.182558534102476,"train_loss":0.11405938588287753,"stage3_test_loss":0.2519704716445699,"_runtime":16,"final_summary_log_path":"/home/qphan/master-thesis/models/uci_best_model_three_stage_channel_subject25_val_final_summary_val_25.txt","stage2/epoch":10,"stage2/best_epoch":1,"stage1/test_loss":0.21086021907105196,"stage2/mask_l1":0.4777069091796875,"block4_Pruned_%":78.125,"stage1_test_loss":0.21086021907105196,"stage2_test_acc":46.182558534102476,"stage2/raw_hard_mask_block2":"[0.0, 1.0, 1.0, 1.0, 0.0, 1.0, 1.0, 0.0, 1.0, 0.0, 0.0, 0.0, 0.0, 0.0, 0.0, 0.0, 0.0, 0.0, 1.0, 0.0, 0.0, 0.0, 0.0, 1.0, 0.0, 0.0, 0.0, 0.0, 1.0, 0.0, 1.0, 1.0, 0.0, 0.0, 0.0, 0.0, 0.0, 0.0, 0.0, 0.0, 0.0, 0.0, 0.0, 0.0, 0.0, 1.0, 0.0, 1.0, 1.0, 1.0, 0.0, 0.0, 0.0, 0.0, 1.0, 0.0, 0.0, 0.0, 1.0, 0.0, 0.0, 0.0, 0.0, 0.0]","stage2_test_f1":0.3013786284501836,"val_loss":0.3360963960185028,"stage2/purpose":"train channel-pruning model with masking","_wandb":{"runtime":16},"stage2/block4_Pruned_%":78.125,"stage1/test_f1":0.9402865062837908,"stage3_test_acc":90.70240922972515,"_step":12,"stage2/final_mask_keep_ratio_block3":0.203125,"stage2_test_loss":1.4132957125179315,"stage2/raw_hard_mask_block3":"[0.0, 0.0, 1.0, 0.0, 0.0, 1.0, 0.0, 1.0, 0.0, 0.0, 1.0, 0.0, 0.0, 1.0, 0.0, 0.0, 1.0, 0.0, 0.0, 0.0, 0.0, 1.0, 0.0, 0.0, 1.0, 0.0, 0.0, 1.0, 0.0, 0.0, 0.0, 0.0, 0.0, 0.0, 0.0, 0.0, 0.0, 0.0, 1.0, 1.0, 0.0, 0.0, 1.0, 0.0, 0.0, 0.0, 0.0, 0.0, 0.0, 0.0, 0.0, 0.0, 0.0, 0.0, 0.0, 0.0, 0.0, 0.0, 0.0, 0.0, 0.0, 0.0, 0.0, 0.0, 0.0, 0.0, 0.0, 1.0, 0.0, 1.0, 0.0, 0.0, 0.0, 0.0, 0.0, 0.0, 0.0, 0.0, 0.0, 0.0, 0.0, 0.0, 0.0, 0.0, 0.0, 0.0, 0.0, 0.0, 0.0, 0.0, 1.0, 0.0, 0.0, 0.0, 0.0, 0.0, 1.0, 1.0, 0.0, 1.0, 1.0, 0.0, 0.0, 0.0, 1.0, 0.0, 0.0, 1.0, 0.0, 1.0, 0.0, 1.0, 0.0, 0.0, 0.0, 0.0, 0.0, 0.0, 0.0, 0.0, 1.0, 1.0, 0.0, 0.0, 0.0, 1.0, 0.0, 0.0]","stage2/test_loss":1.4132957125179315,"stage2/train_acc":77.89140141149359,"stage2/val_acc":42.78728606356968,"val_acc":86.0635696821516,"stage1/use_pretrain_model":false,"stage2/Total_Pruned_%":77.8125,"stage2/train_loss":1.812985049515864,"stage2/final_mask_keep_ratio_block2":0.265625,"stage_3_prunedseparableconvcnn/confusion_matrix_table":{"_type":"table-file","ncols":3,"_latest_artifact_path":"wandb-client-artifact://y1ggi3thrmswjmautr4jhbzd4ygoojt7eghs8dvtcg2adv01mfjxtwo8qb3800or6cjqgnhub203rpqhfl1kmnqqcgs7dlbscpwaumqji8urrcbkj370g94qjtg5w3r5:latest/stage_3_prunedseparableconvcnn/confusion_matrix_table.table.json","size":1363,"sha256":"c682f9ec0a60f1e365e96ecd459778d43df1eca009914663507350ff074780c8","log_mode":"IMMUTABLE","nrows":36,"artifact_path":"wandb-client-artifact://yj6olopigw0eoc5ro4gq6w8yqq5vo7oxauy5c8v8debyc6ov8eoxsxf40pqqo553ucd2okiamu83hq4r6xh6j1prehzpkrlkou1qcbdvg7w5iubhg66cogh9pk70jqa5/stage_3_prunedseparableconvcnn/confusion_matrix_table.table.json","path":"media/table/stage_3_prunedseparableconvcnn/confusion_matrix_table_10_c682f9ec0a60f1e365e9.table.json"},"train_acc":95.1029814201354,"stage2/lr_backbone":0.0001,"epoch":25}