{"stage2/block3_Pruned_%":78.125,"model_param_count_dense":36868,"stage2/raw_hard_mask_block4":"[0.0, 0.0, 1.0, 0.0, 0.0, 0.0, 0.0, 0.0, 0.0, 1.0, 1.0, 0.0, 0.0, 0.0, 0.0, 0.0, 0.0, 1.0, 1.0, 0.0, 0.0, 0.0, 1.0, 0.0, 0.0, 0.0, 0.0, 1.0, 0.0, 0.0, 0.0, 0.0, 0.0, 0.0, 0.0, 0.0, 0.0, 1.0, 0.0, 0.0, 1.0, 0.0, 0.0, 0.0, 0.0, 0.0, 0.0, 0.0, 0.0, 1.0, 0.0, 0.0, 1.0, 1.0, 0.0, 1.0, 1.0, 0.0, 0.0, 0.0, 0.0, 0.0, 0.0, 0.0, 0.0, 0.0, 0.0, 0.0, 1.0, 0.0, 0.0, 0.0, 0.0, 1.0, 0.0, 1.0, 0.0, 0.0, 1.0, 0.0, 1.0, 0.0, 0.0, 0.0, 0.0, 0.0, 0.0, 1.0, 1.0, 0.0, 0.0, 1.0, 1.0, 0.0, 0.0, 0.0, 0.0, 0.0, 0.0, 0.0, 0.0, 0.0, 1.0, 0.0, 0.0, 1.0, 0.0, 0.0, 0.0, 1.0, 0.0, 0.0, 0.0, 0.0, 1.0, 0.0, 0.0, 0.0, 0.0, 0.0, 1.0, 0.0, 0.0, 0.0, 0.0, 1.0, 0.0, 1.0]","model_param_count_pruned":5161,"stage2/best_val_loss":1.3883071433570269,"_timestamp":1.7768013851939337e+09,"stage2/lr_backbone":0.0001,"stage2/final_mask_keep_ratio_block4":0.234375,"stage2/train_loss":1.8219746285723755,"stage1_test_loss":0.3163428130339651,"block4_Pruned_%":76.5625,"stage_3_prunedseparableconvcnn/confusion_matrix_table":{"nrows":36,"_type":"table-file","ncols":3,"_latest_artifact_path":"wandb-client-artifact://n9rmuq06rzhxdt5o956c3yln2ydci7alixaoskbibo0f1r0p3ll1564bn6w2p6u2o2oxxhpep5r0ehy519g1srm501zqk0brtac782w7z428urez79a3nuajtriuk41u:latest/stage_3_prunedseparableconvcnn/confusion_matrix_table.table.json","artifact_path":"wandb-client-artifact://nm6mph3wah2bqeiyaqm6efitu2dmhaq2eq24q5h8x6fkmu26a6hcwxsg49m0fo6yhotlnjqyil08msmp9elkbaaaf41hd7npr1l7ll70nlannro7zchpa5h4ike4stib/stage_3_prunedseparableconvcnn/confusion_matrix_table.table.json","sha256":"7cb9dff15e91d0435c3e5c3aed5cd5486d8fbf1003a0d631b56ac6b67080dea4","size":1363,"log_mode":"IMMUTABLE","path":"media/table/stage_3_prunedseparableconvcnn/confusion_matrix_table_16_7cb9dff15e91d0435c3e.table.json"},"stage2/block4_Pruned_%":76.5625,"val_loss":0.0042119153536405276,"stage2/test_acc":45.402103834407875,"stage1_test_f1":0.9147812515637623,"stage2/val_acc":43.22766570605187,"stage_1_separableconvcnn/confusion_matrix_table":{"sha256":"455af67ee87071128306d26881825081264c3d04288a60e5ae198ffd7a948662","size":1365,"_type":"table-file","log_mode":"IMMUTABLE","path":"media/table/stage_1_separableconvcnn/confusion_matrix_table_1_455af67ee87071128306.table.json","_latest_artifact_path":"wandb-client-artifact://fe1187dotq372akt6r8o7jqjjph0wqjhunwgo54uqqdlxez6su8kgs56pj8dkgglnef82p7dersqkwdvqeh78ox2g6f9qiehh5ajb6cnyayy3le7kn4lr25eezdzckxg:latest/stage_1_separableconvcnn/confusion_matrix_table.table.json","artifact_path":"wandb-client-artifact://8ttuho5q7woqpdkoyplug0d3l29wnzawfpgwdny5icfxe4bp8802sglk1wfccy2i8hfw14mhfgbbnqg87q99kqs43zybnbm87azi5ukqmhlm54tio4e2o9on6lgb1gie/stage_1_separableconvcnn/confusion_matrix_table.table.json","ncols":3,"nrows":36},"best_val_loss":0.004957889063117398,"train_loss":0.08234002966909729,"train_acc":95.97430406852249,"_wandb":{"runtime":30},"block2_Pruned_%":67.1875,"stage1/use_pretrain_model":false,"lr_loaded_weights":0.0001,"stage2_test_f1":0.3211853251270275,"stage2/test_loss":1.4934803006767943,"stage1/test_loss":0.3163428130339651,"_step":18,"stage2_test_loss":1.4934803006767943,"stage1_test_acc":91.41499830335935,"stage2_test_acc":45.402103834407875,"block3_Pruned_%":78.125,"stage2/train_acc":77.64453961456103,"stage2/purpose":"train channel-pruning model with masking","stage3_test_f1":0.9148657864372316,"val_acc":100,"stage1/test_f1":0.9147812515637623,"stage2/block2_Pruned_%":67.1875,"stage2/mask_l1":0.48026764392852783,"stage2/stage_number":2,"model_param_count":5161,"stage2/test_f1":0.3211853251270275,"stage":3,"stage2/raw_hard_mask_block2":"[0.0, 0.0, 0.0, 0.0, 0.0, 0.0, 1.0, 0.0, 0.0, 1.0, 0.0, 1.0, 0.0, 0.0, 1.0, 1.0, 0.0, 1.0, 1.0, 0.0, 0.0, 1.0, 0.0, 0.0, 0.0, 1.0, 0.0, 0.0, 1.0, 1.0, 1.0, 0.0, 1.0, 0.0, 1.0, 1.0, 1.0, 0.0, 0.0, 1.0, 0.0, 0.0, 0.0, 0.0, 0.0, 0.0, 1.0, 0.0, 0.0, 0.0, 1.0, 0.0, 0.0, 0.0, 0.0, 0.0, 0.0, 0.0, 0.0, 1.0, 0.0, 1.0, 0.0, 0.0]","stage2/val_loss":2.9884259900029866,"final_summary_log_path":"/home/qphan/master-thesis/models/uci_best_model_three_stage_channel_subject1_val_final_summary_val_1.txt","stage2/final_mask_keep_ratio_block3":0.21875,"stage3_test_loss":0.34419061806421564,"model_param_reduction_pct":86.00141043723555,"stage2/lr_gumbel":0.001,"_runtime":30,"stage2/epoch":10,"stage2/raw_hard_mask_block3":"[0.0, 0.0, 0.0, 1.0, 0.0, 0.0, 1.0, 1.0, 0.0, 0.0, 0.0, 1.0, 0.0, 0.0, 0.0, 0.0, 0.0, 0.0, 0.0, 0.0, 0.0, 0.0, 1.0, 1.0, 1.0, 0.0, 0.0, 0.0, 0.0, 0.0, 0.0, 0.0, 0.0, 0.0, 0.0, 0.0, 0.0, 0.0, 0.0, 0.0, 1.0, 0.0, 0.0, 0.0, 0.0, 0.0, 1.0, 0.0, 0.0, 0.0, 1.0, 0.0, 1.0, 0.0, 0.0, 0.0, 0.0, 0.0, 0.0, 0.0, 0.0, 0.0, 0.0, 1.0, 0.0, 0.0, 1.0, 0.0, 0.0, 0.0, 0.0, 0.0, 0.0, 0.0, 0.0, 0.0, 0.0, 0.0, 0.0, 0.0, 0.0, 1.0, 0.0, 0.0, 0.0, 0.0, 1.0, 1.0, 0.0, 0.0, 1.0, 0.0, 1.0, 0.0, 1.0, 0.0, 1.0, 0.0, 0.0, 0.0, 0.0, 1.0, 0.0, 1.0, 0.0, 0.0, 1.0, 0.0, 0.0, 0.0, 1.0, 0.0, 1.0, 0.0, 0.0, 0.0, 0.0, 1.0, 1.0, 0.0, 1.0, 0.0, 0.0, 0.0, 0.0, 0.0, 0.0, 0.0]","stage2/final_mask_keep_ratio_block2":0.328125,"epoch":55,"stage3_test_acc":91.48286392941975,"stage1/test_acc":91.41499830335935,"Total_Pruned_%":75.3125,"stage2/best_epoch":4,"stage2/Total_Pruned_%":75.3125}