{"stage2_test_loss":0.6441710843515974,"stage2/Total_Pruned_%":66.25,"stage2/block2_Pruned_%":67.1875,"stage":3,"stage1/use_pretrain_model":false,"stage1_test_acc":92.33118425517475,"block3_Pruned_%":70.3125,"stage2/test_loss":0.6441710843515974,"stage2/train_acc":59.90816472951643,"stage1/test_loss":0.22055789638881276,"block2_Pruned_%":67.1875,"val_loss":0.22917877880378576,"model_param_reduction_pct":79.12281653466421,"stage2/best_epoch":27,"best_val_loss":0.21152783701939182,"stage1/test_acc":92.33118425517475,"stage2/raw_hard_mask_block2":"[1.0, 0.0, 1.0, 0.0, 0.0, 0.0, 1.0, 0.0, 0.0, 0.0, 0.0, 0.0, 0.0, 0.0, 0.0, 0.0, 1.0, 0.0, 1.0, 0.0, 0.0, 0.0, 1.0, 1.0, 0.0, 0.0, 1.0, 0.0, 0.0, 0.0, 1.0, 0.0, 0.0, 1.0, 0.0, 0.0, 0.0, 0.0, 1.0, 0.0, 0.0, 1.0, 1.0, 1.0, 1.0, 0.0, 1.0, 1.0, 0.0, 0.0, 0.0, 1.0, 0.0, 0.0, 0.0, 1.0, 1.0, 0.0, 0.0, 0.0, 0.0, 1.0, 0.0, 0.0]","stage2/stage_number":2,"model_param_count_pruned":7697,"stage2/block3_Pruned_%":70.3125,"lr_loaded_weights":0.0001,"stage2/mask_l1":0.42714449763298035,"stage3_test_loss":0.36244487800956715,"stage2/best_val_loss":0.5500372825555173,"stage2/final_mask_keep_ratio_block3":0.296875,"stage2/test_f1":0.6576584654995963,"_wandb":{"runtime":41},"stage2_test_f1":0.6576584654995963,"stage2/final_mask_keep_ratio_block2":0.328125,"stage2/test_acc":67.1869697997964,"stage1_test_loss":0.22055789638881276,"model_param_count_dense":36868,"stage2/epoch":35,"Total_Pruned_%":66.25,"block4_Pruned_%":61.71875,"stage2/raw_hard_mask_block3":"[0.0, 0.0, 1.0, 1.0, 1.0, 0.0, 1.0, 0.0, 0.0, 1.0, 0.0, 1.0, 0.0, 1.0, 1.0, 0.0, 0.0, 0.0, 0.0, 1.0, 1.0, 0.0, 0.0, 0.0, 1.0, 0.0, 1.0, 0.0, 1.0, 1.0, 0.0, 0.0, 1.0, 1.0, 0.0, 1.0, 1.0, 0.0, 0.0, 1.0, 0.0, 0.0, 1.0, 0.0, 0.0, 0.0, 0.0, 0.0, 0.0, 1.0, 0.0, 0.0, 0.0, 0.0, 0.0, 1.0, 0.0, 0.0, 0.0, 1.0, 0.0, 0.0, 0.0, 0.0, 1.0, 0.0, 0.0, 0.0, 1.0, 0.0, 0.0, 0.0, 0.0, 1.0, 0.0, 0.0, 1.0, 0.0, 0.0, 1.0, 0.0, 0.0, 0.0, 0.0, 0.0, 0.0, 1.0, 0.0, 1.0, 0.0, 1.0, 0.0, 0.0, 1.0, 0.0, 0.0, 1.0, 0.0, 0.0, 1.0, 0.0, 0.0, 0.0, 0.0, 0.0, 1.0, 0.0, 0.0, 0.0, 0.0, 0.0, 0.0, 1.0, 0.0, 0.0, 0.0, 0.0, 0.0, 0.0, 0.0, 0.0, 1.0, 0.0, 0.0, 0.0, 0.0, 1.0, 0.0]","stage2/block4_Pruned_%":61.71875,"stage2/raw_hard_mask_block4":"[1.0, 1.0, 1.0, 1.0, 0.0, 0.0, 0.0, 1.0, 1.0, 1.0, 1.0, 0.0, 0.0, 0.0, 1.0, 1.0, 1.0, 0.0, 0.0, 0.0, 0.0, 0.0, 1.0, 1.0, 1.0, 0.0, 0.0, 1.0, 0.0, 1.0, 0.0, 1.0, 1.0, 1.0, 0.0, 0.0, 0.0, 0.0, 0.0, 0.0, 1.0, 0.0, 0.0, 0.0, 0.0, 0.0, 1.0, 0.0, 0.0, 0.0, 0.0, 0.0, 0.0, 0.0, 0.0, 0.0, 1.0, 1.0, 0.0, 0.0, 1.0, 1.0, 1.0, 0.0, 0.0, 1.0, 0.0, 1.0, 0.0, 0.0, 0.0, 1.0, 0.0, 0.0, 1.0, 0.0, 0.0, 0.0, 0.0, 1.0, 1.0, 0.0, 0.0, 0.0, 0.0, 0.0, 0.0, 1.0, 0.0, 0.0, 1.0, 0.0, 0.0, 0.0, 1.0, 0.0, 1.0, 0.0, 0.0, 0.0, 1.0, 1.0, 1.0, 1.0, 1.0, 0.0, 0.0, 0.0, 1.0, 0.0, 0.0, 1.0, 0.0, 1.0, 1.0, 0.0, 0.0, 0.0, 1.0, 0.0, 1.0, 1.0, 0.0, 0.0, 0.0, 1.0, 0.0, 0.0]","_timestamp":1.775864654480578e+09,"stage2/train_loss":0.9860884875405517,"stage_3_prunedseparableconvcnn/confusion_matrix_table":{"path":"media/table/stage_3_prunedseparableconvcnn/confusion_matrix_table_22_69d46cdc8ad620d4e682.table.json","nrows":36,"sha256":"69d46cdc8ad620d4e682d009ba5f6db588878a0671109fe7ba0dee2c649f00d5","size":1367,"_type":"table-file","log_mode":"IMMUTABLE","_latest_artifact_path":"wandb-client-artifact://9elbaxtvcrxzudifv60axwoghhaitkydmcvbljowo3n88l2757ee0n9bsrs2hg4rgsmji7w0uv2ud8jqkzlgbzlfo2poc9c0cw1sd3iwq5ppql3dq86ohpubeiq14zz5:latest/stage_3_prunedseparableconvcnn/confusion_matrix_table.table.json","ncols":3,"artifact_path":"wandb-client-artifact://yh0lc8mbbay93o5vqwz3tn1b5r4u3wq03pqm2jll3qev9tpqiskllx6fk0s7iyz8vhkw7o7n2zm6mfln6igkdxzjjn7jmd94i314mxbijzr2ix4e0q0g7ttzrzari7ln/stage_3_prunedseparableconvcnn/confusion_matrix_table.table.json"},"stage1/test_f1":0.9239060078892737,"stage2/val_loss":0.5587343223704215,"epoch":60,"stage2/val_acc":64.49086161879896,"_step":24,"stage2_test_acc":67.1869697997964,"stage1_test_f1":0.9239060078892737,"stage2/lr_backbone":0.0001,"stage3_test_f1":0.8787607101245478,"model_param_count":7697,"val_acc":90.07832898172323,"stage2/final_mask_keep_ratio_block4":0.3828125,"stage_1_separableconvcnn/confusion_matrix_table":{"nrows":36,"_latest_artifact_path":"wandb-client-artifact://zt696ppq2ancrs057vmu56cs2xnu7221ss716xh7mg54jyxqxc0c7hs1k8t7zphtatcb5s2b9yr2a7cwc92d3ycos98unvumcs7f99zj7yx86nubyfy8zo0yddgrw1fc:latest/stage_1_separableconvcnn/confusion_matrix_table.table.json","path":"media/table/stage_1_separableconvcnn/confusion_matrix_table_1_cc7b9f814993e0a95cb9.table.json","log_mode":"IMMUTABLE","sha256":"cc7b9f814993e0a95cb917ba11f19db645c604b66bb7ffecd44ad2ccf6147a1e","ncols":3,"artifact_path":"wandb-client-artifact://o2p5uutoba7819lxbpw403t0c71j2x4o0r5n053axodtn9upqldswqkjvkk1373g3hiniuo1ukxyw5x5x1z07siqo8v98czw5rzuevnpfsicjr4hkjgkbvfm5411p9q2/stage_1_separableconvcnn/confusion_matrix_table.table.json","_type":"table-file","size":1368},"_runtime":41,"stage2/lr_gumbel":0.001,"stage2/purpose":"train channel-pruning model with masking","train_loss":0.2719771879242592,"final_summary_log_path":"/home/qphan/master-thesis/models/uci_best_model_three_stage_channel_subject30_val_final_summary_val_30.txt","train_acc":88.21925670827953,"stage3_test_acc":87.64845605700712}