{"val_acc":73.63921345112567,"stage3_test_acc":69.26326635754765,"stage3_test_f1":0.6276822065626733,"channels_block4":38,"lr":0.001,"stage_1_separableconvcnn/confusion_matrix_table":{"artifact_path":"wandb-client-artifact://ea7zkknrywj41a6pw9ivnn074kbinyj25zgnl9edskappqllgyi37t3nfbiw4iha2adv5wsjbbw61egq77ykd8xv72zuaukqyb0j2khkap5wg4q6ctt8cpezncq4ytre/stage_1_separableconvcnn/confusion_matrix_table.table.json","sha256":"9801ff5ef3ee6a3bb05a05ebf42ad249b8e3a430a027e67d8bea790f448fb438","log_mode":"IMMUTABLE","path":"media/table/stage_1_separableconvcnn/confusion_matrix_table_0_9801ff5ef3ee6a3bb05a.table.json","_type":"table-file","_latest_artifact_path":"wandb-client-artifact://am0bsmus0000z24vshnte89pqps4b4bi2jyg5slt1gvspne1edjn6hwkr2aymzarzyk47xkbku9tnxf4cgwienvpp56z1kw08wwx7hfoqpyq2i52pt4x1n8hnu559g67:latest/stage_1_separableconvcnn/confusion_matrix_table.table.json","nrows":64,"ncols":3,"size":2014},"stage3_channel_metadata_json":"{\"block2\": {\"kept_indices\": [0, 3, 6, 12, 13, 14, 16, 19, 21, 28, 32, 35, 43, 45, 47, 48, 49, 54, 55], \"pruned_indices\": [1, 2, 4, 5, 7, 8, 9, 10, 11, 15, 17, 18, 20, 22, 23, 24, 25, 26, 27, 29, 30, 31, 33, 34, 36, 37, 38, 39, 40, 41, 42, 44, 46, 50, 51, 52, 53, 56, 57, 58, 59, 60, 61, 62, 63], \"kept_count\": 19, \"pruned_count\": 45, \"total_channels\": 64}, \"block3\": {\"kept_indices\": [1, 2, 7, 8, 11, 12, 17, 20, 22, 24, 25, 27, 29, 30, 32, 34, 35, 37, 38, 44, 47, 48, 49, 50, 54, 57, 59, 62, 65, 69, 73, 83, 96, 99, 101, 121, 122, 125], \"pruned_indices\": [0, 3, 4, 5, 6, 9, 10, 13, 14, 15, 16, 18, 19, 21, 23, 26, 28, 31, 33, 36, 39, 40, 41, 42, 43, 45, 46, 51, 52, 53, 55, 56, 58, 60, 61, 63, 64, 66, 67, 68, 70, 71, 72, 74, 75, 76, 77, 78, 79, 80, 81, 82, 84, 85, 86, 87, 88, 89, 90, 91, 92, 93, 94, 95, 97, 98, 100, 102, 103, 104, 105, 106, 107, 108, 109, 110, 111, 112, 113, 114, 115, 116, 117, 118, 119, 120, 123, 124, 126, 127], \"kept_count\": 38, \"pruned_count\": 90, \"total_channels\": 128}, \"block4\": {\"kept_indices\": [0, 1, 3, 6, 18, 19, 20, 22, 23, 25, 26, 27, 34, 35, 39, 50, 51, 53, 56, 60, 65, 71, 72, 73, 75, 77, 78, 81, 82, 86, 87, 91, 93, 100, 101, 107, 113, 119], \"pruned_indices\": [2, 4, 5, 7, 8, 9, 10, 11, 12, 13, 14, 15, 16, 17, 21, 24, 28, 29, 30, 31, 32, 33, 36, 37, 38, 40, 41, 42, 43, 44, 45, 46, 47, 48, 49, 52, 54, 55, 57, 58, 59, 61, 62, 63, 64, 66, 67, 68, 69, 70, 74, 76, 79, 80, 83, 84, 85, 88, 89, 90, 92, 94, 95, 96, 97, 98, 99, 102, 103, 104, 105, 106, 108, 109, 110, 111, 112, 114, 115, 116, 117, 118, 120, 121, 122, 123, 124, 125, 126, 127], \"kept_count\": 38, \"pruned_count\": 90, \"total_channels\": 128}}","best_val_loss":0.6987257918322246,"_runtime":94,"_step":9,"epoch":28,"stage1_test_acc":78.49562081401339,"_timestamp":1.7754374342939837e+09,"channels_block3":38,"train_loss":0.6413622505824185,"val_loss":0.7900158068025578,"channels_block2":19,"stage":3,"stage1_test_f1":0.677967605576644,"train_acc":76.62997798679207,"stage_3_prunedseparableconvcnn/confusion_matrix_table":{"artifact_path":"wandb-client-artifact://x9gwawztcyafgpqaf2w88zlymphis1aefnk49y30nb4uw8vukykb6rysjiw4889x2vhiz11b0gikuus6yb6cl24obocbig008lzbbrnnrh5lde6h564kou8dweb625va/stage_3_prunedseparableconvcnn/confusion_matrix_table.table.json","_latest_artifact_path":"wandb-client-artifact://k80cmc9zjnsohwrttzesix0pho0b225uithbcslgagomoideb0c4ypnlr87bg915k1mm48iafsnhc73f8nw05j3vhteask18xje7fv1mis4gqa5rpabgtv2hzhof4yt9:latest/stage_3_prunedseparableconvcnn/confusion_matrix_table.table.json","path":"media/table/stage_3_prunedseparableconvcnn/confusion_matrix_table_8_fc664fbea1e3cb40b418.table.json","log_mode":"IMMUTABLE","ncols":3,"_type":"table-file","sha256":"fc664fbea1e3cb40b418e197c9b0c161178d7e60d8ff7fae245609fc5545135f","nrows":64,"size":2013},"params_before_pruning":36998,"_wandb":{"runtime":94},"stage3_final_mask_json":"{\"block2\": [1.0, 0.0, 0.0, 1.0, 0.0, 0.0, 1.0, 0.0, 0.0, 0.0, 0.0, 0.0, 1.0, 1.0, 1.0, 0.0, 1.0, 0.0, 0.0, 1.0, 0.0, 1.0, 0.0, 0.0, 0.0, 0.0, 0.0, 0.0, 1.0, 0.0, 0.0, 0.0, 1.0, 0.0, 0.0, 1.0, 0.0, 0.0, 0.0, 0.0, 0.0, 0.0, 0.0, 1.0, 0.0, 1.0, 0.0, 1.0, 1.0, 1.0, 0.0, 0.0, 0.0, 0.0, 1.0, 1.0, 0.0, 0.0, 0.0, 0.0, 0.0, 0.0, 0.0, 0.0], \"block3\": [0.0, 1.0, 1.0, 0.0, 0.0, 0.0, 0.0, 1.0, 1.0, 0.0, 0.0, 1.0, 1.0, 0.0, 0.0, 0.0, 0.0, 1.0, 0.0, 0.0, 1.0, 0.0, 1.0, 0.0, 1.0, 1.0, 0.0, 1.0, 0.0, 1.0, 1.0, 0.0, 1.0, 0.0, 1.0, 1.0, 0.0, 1.0, 1.0, 0.0, 0.0, 0.0, 0.0, 0.0, 1.0, 0.0, 0.0, 1.0, 1.0, 1.0, 1.0, 0.0, 0.0, 0.0, 1.0, 0.0, 0.0, 1.0, 0.0, 1.0, 0.0, 0.0, 1.0, 0.0, 0.0, 1.0, 0.0, 0.0, 0.0, 1.0, 0.0, 0.0, 0.0, 1.0, 0.0, 0.0, 0.0, 0.0, 0.0, 0.0, 0.0, 0.0, 0.0, 1.0, 0.0, 0.0, 0.0, 0.0, 0.0, 0.0, 0.0, 0.0, 0.0, 0.0, 0.0, 0.0, 1.0, 0.0, 0.0, 1.0, 0.0, 1.0, 0.0, 0.0, 0.0, 0.0, 0.0, 0.0, 0.0, 0.0, 0.0, 0.0, 0.0, 0.0, 0.0, 0.0, 0.0, 0.0, 0.0, 0.0, 0.0, 1.0, 1.0, 0.0, 0.0, 1.0, 0.0, 0.0], \"block4\": [1.0, 1.0, 0.0, 1.0, 0.0, 0.0, 1.0, 0.0, 0.0, 0.0, 0.0, 0.0, 0.0, 0.0, 0.0, 0.0, 0.0, 0.0, 1.0, 1.0, 1.0, 0.0, 1.0, 1.0, 0.0, 1.0, 1.0, 1.0, 0.0, 0.0, 0.0, 0.0, 0.0, 0.0, 1.0, 1.0, 0.0, 0.0, 0.0, 1.0, 0.0, 0.0, 0.0, 0.0, 0.0, 0.0, 0.0, 0.0, 0.0, 0.0, 1.0, 1.0, 0.0, 1.0, 0.0, 0.0, 1.0, 0.0, 0.0, 0.0, 1.0, 0.0, 0.0, 0.0, 0.0, 1.0, 0.0, 0.0, 0.0, 0.0, 0.0, 1.0, 1.0, 1.0, 0.0, 1.0, 0.0, 1.0, 1.0, 0.0, 0.0, 1.0, 1.0, 0.0, 0.0, 0.0, 1.0, 1.0, 0.0, 0.0, 0.0, 1.0, 0.0, 1.0, 0.0, 0.0, 0.0, 0.0, 0.0, 0.0, 1.0, 1.0, 0.0, 0.0, 0.0, 0.0, 0.0, 1.0, 0.0, 0.0, 0.0, 0.0, 0.0, 1.0, 0.0, 0.0, 0.0, 0.0, 0.0, 1.0, 0.0, 0.0, 0.0, 0.0, 0.0, 0.0, 0.0, 0.0]}","params_after_pruning":6533}